duckup/__init__.py
duckup/cli.py
duckup/migrate.py
duckup/queries.py
duckup-1.0.0.dist-info/LICENSE.md
duckup-1.0.0.dist-info/METADATA
duckup-1.0.0.dist-info/WHEEL
duckup-1.0.0.dist-info/entry_points.txt
duckup-1.0.0.dist-info/RECORD
