Metadata-Version: 2.3
Name: duckup
Version: 1.0.0
Summary: Database migrations for DuckDB.
License: MIT
Author: Oleksandr Reshetniak
Requires-Python: >=3.9
Classifier: Intended Audience :: Developers
Classifier: License :: OSI Approved :: MIT License
Classifier: Operating System :: MacOS :: MacOS X
Classifier: Operating System :: Microsoft :: Windows
Classifier: Operating System :: POSIX :: Linux
Classifier: Programming Language :: Python :: 3
Classifier: Programming Language :: Python :: 3.9
Classifier: Programming Language :: Python :: 3.10
Classifier: Programming Language :: Python :: 3.11
Classifier: Programming Language :: Python :: 3.12
Classifier: Programming Language :: Python :: 3.13
Classifier: Topic :: Database
Classifier: Topic :: Software Development :: Libraries :: Python Modules
Requires-Dist: duckdb (>=1.2.0,<2)
Project-URL: Homepage, https://github.com/akares/duckup-py
Project-URL: Repository, https://github.com/akares/duckup-py
